shade_privacy/__init__.py
shade_privacy/__version__.py
shade_privacy/exceptions.py
shade_privacy/sdk.py
shade_privacy/utils/__init__.py
shade_privacy/utils/encrypt.py
shade_privacy/utils/sign.py
shade_privacy/utils/websockets.py
shade_privacy-1.0.3.dist-info/METADATA
shade_privacy-1.0.3.dist-info/WHEEL
shade_privacy-1.0.3.dist-info/top_level.txt
shade_privacy-1.0.3.dist-info/RECORD
