Metadata-Version: 2.4
Name: shade-privacy
Version: 1.0.3
Summary: Python SDK for private cross-chain transactions with ZK proofs. Supports ETH, SOL, StarkNet, Base, Sei, AVAX, SUI + 13 chains.
Home-page: https://github.com/Shade-privacy/python-sdk
Author: Shade Privacy
Author-email: ikinyapeter93@gmail.com
License: MIT
Project-URL: Homepage, https://shadeprivacy.com
Project-URL: Documentation, https://docs.shadeprivacy.com
Project-URL: Source Code, https://github.com/Shade-privacy/python-sdk
Project-URL: Bug Tracker, https://github.com/Shade-privacy/python-sdk/issues
Project-URL: Changelog, https://github.com/Shade-privacy/python-sdk/releases
Project-URL: Discord, https://discord.gg/shade-privacy
Project-URL: Twitter, https://twitter.com/shade_privacy
Keywords: privacy,blockchain,zk,zero-knowledge,cross-chain,ethereum,solana,starknet,cryptocurrency,web3
Classifier: Development Status :: 4 - Beta
Classifier: Intended Audience :: Developers
Classifier: Topic :: Software Development :: Libraries :: Python Modules
Classifier: Topic :: Security :: Cryptography
Classifier: License :: OSI Approved :: MIT License
Classifier: Programming Language :: Python :: 3
Classifier: Programming Language :: Python :: 3.8
Classifier: Programming Language :: Python :: 3.9
Classifier: Programming Language :: Python :: 3.10
Classifier: Programming Language :: Python :: 3.11
Classifier: Operating System :: OS Independent
Requires-Python: >=3.8
Requires-Dist: requests>=2.28.0
Requires-Dist: websockets>=11.0.0
Requires-Dist: pycryptodome>=3.17.0
Provides-Extra: dev
Requires-Dist: pytest>=7.0.0; extra == "dev"
Requires-Dist: pytest-asyncio>=0.20.0; extra == "dev"
Requires-Dist: black>=22.0.0; extra == "dev"
Requires-Dist: isort>=5.0.0; extra == "dev"
Requires-Dist: mypy>=1.0.0; extra == "dev"
Requires-Dist: flake8>=5.0.0; extra == "dev"
Dynamic: author
Dynamic: author-email
Dynamic: classifier
Dynamic: description
Dynamic: description-content-type
Dynamic: home-page
Dynamic: keywords
Dynamic: project-url
Dynamic: requires-dist
Dynamic: requires-python
Dynamic: summary
